lazytoolz/__init__.py
lazytoolz/lazylist.py
lazytoolz-0.1.6.dist-info/LICENSE
lazytoolz-0.1.6.dist-info/METADATA
lazytoolz-0.1.6.dist-info/WHEEL
lazytoolz-0.1.6.dist-info/top_level.txt
lazytoolz-0.1.6.dist-info/RECORD
