Metadata-Version: 2.1
Name: lazytoolz
Version: 0.1.6
Summary: Tools for lazy programming in Python
Author: adesanjo
License: MIT License        
Project-URL: Homepage, https://github.com/adesanjo/lazytoolz
Keywords: lazy,tool,tools,toolz,lazytoolz,lazylist
Classifier: License :: OSI Approved :: MIT License
Classifier: Programming Language :: Python
Classifier: Programming Language :: Python :: 3
Requires-Python: >=3.10
License-File: LICENSE
Provides-Extra: dev
